ptsandbox/__init__.py
ptsandbox/config.py
ptsandbox/py.typed
ptsandbox/models/__init__.py
ptsandbox/models/api/__init__.py
ptsandbox/models/api/analysis.py
ptsandbox/models/api/key.py
ptsandbox/models/api/maintenance.py
ptsandbox/models/api/sandbox.py
ptsandbox/models/api/scan.py
ptsandbox/models/api/storage.py
ptsandbox/models/core/__init__.py
ptsandbox/models/core/base.py
ptsandbox/models/core/common.py
ptsandbox/models/core/enum.py
ptsandbox/models/ui/__init__.py
ptsandbox/models/ui/artifacts.py
ptsandbox/models/ui/av_engines.py
ptsandbox/models/ui/baqueue.py
ptsandbox/models/ui/cluster.py
ptsandbox/models/ui/common.py
ptsandbox/models/ui/components.py
ptsandbox/models/ui/entry_points.py
ptsandbox/models/ui/license.py
ptsandbox/models/ui/scans.py
ptsandbox/models/ui/storage.py
ptsandbox/models/ui/system.py
ptsandbox/models/ui/tasks.py
ptsandbox/models/ui/tokens.py
ptsandbox/models/ui/tree.py
ptsandbox/sandbox/__init__.py
ptsandbox/sandbox/sandbox.py
ptsandbox/sandbox/sandbox_api.py
ptsandbox/sandbox/sandbox_ui.py
ptsandbox/utils/__init__.py
ptsandbox/utils/async_http_client.py
ptsandbox/utils/diff.py
ptsandbox-5.0.7.dist-info/METADATA
ptsandbox-5.0.7.dist-info/WHEEL
ptsandbox-5.0.7.dist-info/licenses/LICENSE
ptsandbox-5.0.7.dist-info/RECORD
