Metadata-Version: 2.4
Name: ptsandbox
Version: 5.0.7
Summary: Async API connector for PT Sandbox instances
Project-URL: Homepage, https://github.com/Security-Experts-Community/py-ptsandbox
Project-URL: Documentation, https://security-experts-community.github.io/py-ptsandbox
Project-URL: Repository, https://github.com/Security-Experts-Community/py-ptsandbox
Project-URL: Issues, https://github.com/Security-Experts-Community/py-ptsandbox/issues
Author: Alexey Kolesnikov, Dmitry Zotov, PT ESC Malware Detection
License-Expression: MIT
License-File: LICENSE
Keywords: ptsandbox,sandbox
Classifier: Operating System :: OS Independent
Classifier: Programming Language :: Python :: 3
Requires-Python: <4.0,>=3.11
Requires-Dist: aiohttp-socks>=0.11.0
Requires-Dist: aiohttp>=3.13.2
Requires-Dist: loguru>=0.7.3
Requires-Dist: orjson>=3.11.3
Requires-Dist: pydantic>=2.11.7
